setup.py
fcdist_probability/Binomialdistribution.py
fcdist_probability/Gaussiandistribution.py
fcdist_probability/Generaldistribution.py
fcdist_probability/__init__.py
fcdist_probability.egg-info/PKG-INFO
fcdist_probability.egg-info/SOURCES.txt
fcdist_probability.egg-info/dependency_links.txt
fcdist_probability.egg-info/not-zip-safe
fcdist_probability.egg-info/top_level.txt